nlp_analyser/__init__.py
nlp_analyser/analyser.py
nlp_analyser/cli.py
nlp_analyser/converter.py
nlp_analyser/gui.py
nlp_analyser/utils.py
botpress_analyser-0.1.3.dist-info/entry_points.txt
botpress_analyser-0.1.3.dist-info/LICENSE
botpress_analyser-0.1.3.dist-info/WHEEL
botpress_analyser-0.1.3.dist-info/METADATA
botpress_analyser-0.1.3.dist-info/RECORD
