Metadata-Version: 2.1
Name: botpress-analyser
Version: 0.1.3
Summary: A package to make clusters from a corpus
Home-page: https://botpress.com/
License: AGPL-3.0-or-later
Keywords: nlp,chatbot
Author: Pierre Snell
Author-email: pierre.snell@botpress.com
Maintainer: Pierre Snell
Maintainer-email: ierezell@gmail.com
Requires-Python: >=3.7,<3.10
Classifier: License :: OSI Approved :: GNU Affero General Public License v3 or later (AGPLv3+)
Classifier: Programming Language :: Python :: 3
Classifier: Programming Language :: Python :: 3.7
Classifier: Programming Language :: Python :: 3.8
Classifier: Programming Language :: Python :: 3.9
Requires-Dist: LanguageIdentifier (==1.1.1)
Requires-Dist: bertopic (==0.9.4)
Requires-Dist: click (==8.0.4)
Requires-Dist: numba (==0.55.1)
Requires-Dist: numpy (==1.21.5)
Requires-Dist: pandas-profiling (==3.1.0)
Requires-Dist: rich (==11.1.0)
Requires-Dist: spacy (==3.2.1)
Requires-Dist: streamlit (==1.8.0)
Project-URL: Documentation, https://github.com/botpress/solutions/tree/ps_revamp_nlu_testing/custom_tools/NLP_Analyser
Project-URL: Repository, https://github.com/botpress/solutions/tree/ps_revamp_nlu_testing/custom_tools/NLP_Analyser
